{
  "projects": [
    {
      "id": 1,
      "title": "Create new page 22",
      "details": "sample details for pr 122",
      "complete": true
    },
    {
      "id": 3,
      "title": "Create dictionary app 3",
      "details": "sample details for pr 23 \nsample details for pr 23 sample details for pr 23sample details for pr 23",
      "complete": false
    },
    {
      "title": "asd",
      "details": "sample details for pr 23sample details for pr 23sample details for pr 23sample details for pr 23",
      "complete": false,
      "id": 4
    },
    {
      "title": "Create new page 22",
      "details": "",
      "complete": false,
      "id": 5
    },
    {
      "title": "adawdwa",
      "details": "",
      "complete": true,
      "id": 6
    },
    {
      "title": "asdada",
      "details": "sdadasdas",
      "complete": false,
      "id": 7
    },
    {
      "title": "asdawd",
      "details": "adwadwa",
      "complete": true,
      "id": 8
    },
    {
      "title": "asda",
      "details": "ads",
      "complete": false,
      "id": 9
    },
    {
      "title": "ada",
      "details": "adad",
      "complete": true,
      "id": 10
    },
    {
      "title": "addadwdw",
      "details": "adad",
      "complete": false,
      "id": 11
    },
    {
      "title": "awdad",
      "details": "adad",
      "complete": true,
      "id": 12
    },
    {
      "title": "awda",
      "details": "awd",
      "complete": false,
      "id": 13
    },
    {
      "title": "یزز",
      "details": "زظیزظی",
      "complete": false,
      "id": 14
    }
  ]
}